fedrf4panod/__init__.py
fedrf4panod/federated_random_forest_helper.py
fedrf4panod/local_random_forest_helper.py
fedrf4panod/model_serializer.py
fedrf4panod/federated_random_forest_classifier/__init__.py
fedrf4panod/federated_random_forest_classifier/federated_random_forest_cls.py
fedrf4panod/federated_random_forest_classifier/local_random_forest_cls.py
fedrf4panod/federated_random_forest_regressor/__init__.py
fedrf4panod/federated_random_forest_regressor/federated_random_forest_reg.py
fedrf4panod/federated_random_forest_regressor/local_random_forest_reg.py
fedrf4panod-0.0.2.dist-info/licenses/LICENSE
fedrf4panod-0.0.2.dist-info/licenses/LICENSE_scikit-learn
fedrf4panod-0.0.2.dist-info/METADATA
fedrf4panod-0.0.2.dist-info/WHEEL
fedrf4panod-0.0.2.dist-info/top_level.txt
fedrf4panod-0.0.2.dist-info/RECORD
