Metadata-Version: 2.4
Name: fedrf4panod
Version: 0.0.2
Summary: Federated Random Forest for non overlapping features python package.
Home-page: https://gitlab.gwdg.de/cdss/fairpact/fedrf4panod_pip
Author: Amirreza Aleyasin - Youngjun Park - Cord Schmidt - Lion Philip Wolf
Author-email: amirreza.alise@gmail.com
License: MIT
Requires-Python: >=3.9
License-File: LICENSE
License-File: LICENSE_scikit-learn
Requires-Dist: numpy>=1.26.1
Requires-Dist: pandas>=1.5.3
Requires-Dist: scikit-learn>=1.3.2
Dynamic: author
Dynamic: author-email
Dynamic: home-page
Dynamic: license
Dynamic: license-file
Dynamic: requires-dist
Dynamic: requires-python
Dynamic: summary
